{
  "legislative_session": "2026A",
  "identifier": "HB 1418",
  "title": "Online Add-on Transaction Fee Youth Service Enterprise",
  "from_organization": "~{\"classification\": \"lower\"}",
  "classification": [
    "bill"
  ],
  "subject": [
    "Children & Domestic Matters"
  ],
  "abstracts": [
    {
      "note": "summary",
      "abstract": "The act requires each covered social media platform (covered platform) to impose a fee on each add-on transaction that occurs on the covered platform. The act creates the youth mental health services access enterprise in the behavioral health administration (BHA) to use the fee revenue to operate and fund programs that provide youth mental health services. The youth mental health services access enterprise constitutes an enterprise for purposes of section 20 of article X of the state constitution.\u00a0\u00a0\u00a0\u00a0\u00a0The act defines a 'covered platform' as a sole proprietorship, a partnership, a limited liability company, a corporation, an association, or another legal entity, or an affiliate thereof, that:Conducts business in this state;Generates revenue directly from add-on transactions conducted in an online gaming service, product, or feature;Generates a majority of its annual revenue from online gaming services, products, or features;Publishes one or more online gaming services, products, or features that are reasonably likely to be accessed by a youth;Collects users' personal data or has users' personal data collected on its behalf; andDetermines the purposes and means of the processing of users' personal data.\u00a0\u00a0\u00a0\u00a0\u00a0The act defines an 'add-on transaction' as a transaction through which a player or participant in a video game accessed via an online gaming service, product, or feature acquires:An item or ability that provides the player or participant an advantage over other players or participants of the video game; orA feature that alters or enhances the video game as accessed by the online gaming service, product, or feature.\u00a0\u00a0\u00a0\u00a0\u00a0The act creates the youth mental health services access enterprise fund, consisting of money credited to the fund as fee revenue, any money received from the issuance of revenue bonds, and any other money that the general assembly may appropriate or transfer to the youth mental health services access enterprise fund. Money in the youth mental health services access enterprise fund is continuously appropriated to the youth mental health services access enterprise.\u00a0\u00a0\u00a0\u00a0\u00a0After deducting its administrative expenses, the youth mental health services access enterprise is required to allocate the remaining fee revenue credited to the fund as follows:40% to operate and fund the youth mental health peer navigator grant program, which program is created in the act;35% to operate and fund the crisis resolution team program, which program is created in the act; and25%, beginning January 1, 2028, to operate the existing youth mental health services program.\u00a0\u00a0\u00a0\u00a0\u00a0The initial amount of the fee is 5% of the amount of the add-on transaction. On and after October 1, 2027, the youth mental health services access enterprise may adjust the amount of the fee.\u00a0\u00a0\u00a0\u00a0\u00a0The act creates the youth mental health peer navigator grant program to award grants to entities that recruit and train young adults to provide prevention services, peer support, and system navigation to youth in schools or community-based settings.\u00a0\u00a0\u00a0\u00a0\u00a0The act creates the crisis resolution team program to provide community-based de-escalation and stabilization services to youth who are experiencing high-acuity behavioral health crises and to their caregivers.\u00a0\u00a0\u00a0\u00a0\u00a0Under current law, the BHA operates the youth mental health services program to facilitate access to mental health services, including substance use disorder services, for youth in response to mental health needs identified in an initial mental health screening through the program's web-based portal. The youth mental health services program reimburses providers for up to 3 mental health sessions with a youth. The act directs the youth mental health services access enterprise, rather than the BHA, to operate and fund the youth mental health services program beginning January 1, 2028. The act also allows the youth mental health services access enterprise to reimburse a provider for up to 6 mental health sessions with a youth.\u00a0\u00a0\u00a0\u00a0\u00a0The act creates the youth programming and protections enterprise to:Award grants through the existing out-of-school time program grant program; andSupport the department of education's enforcement of educational rights on behalf of children.\u00a0\u00a0\u00a0\u00a0\u00a0The youth programming and protections enterprise constitutes an enterprise for purposes of section 20 of article X of the state constitution.\u00a0\u00a0\u00a0\u00a0\u00a0The act creates the youth programming and protections enterprise fund. In each state fiscal year, after the state treasurer has credited $8 million to the youth mental health services access enterprise fund, the state treasurer must credit any other money received as fees to the youth programming and protections enterprise fund.\u00a0\u00a0\u00a0\u00a0\u00a0Under current law, the department of education administers the out-of-school time program grant program and the state board of education awards grants from the program, subject to available appropriations. The act directs the department of education to consult with the youth programming and protections enterprise in administering the out-of-school time program grant program, and the act directs the youth programming and protections enterprise to award grants from the program in consultation with the state board of education. The act also requires the out-of-school time program grant program to provide programming and services that support the mental health and well-being of children and youth.\u00a0\u00a0\u00a0\u00a0\u00a0The act requires a covered platform to ensure that the purchase price for an online gaming service, product, or feature that is reasonably likely to be accessed by a minor to be listed in United States dollars at the point of sale.\u00a0\u00a0\u00a0\u00a0\u00a0For the 2026-27 state fiscal year, the act appropriates:$294,984 to the department of revenue from the general fund;$26,500 to the department of law from reappropriated funds;$145,750 to the department of law from the youth mental services access enterprise fund created in the act; and$79,500 to the department of law from the youth programming and protections enterprise fund created in the act.(Note: This summary applies to this bill as enacted.)"
    }
  ],
  "other_titles": [],
  "other_identifiers": [
    {
      "identifier": "ocd-bill-co-2026a-hb1418"
    }
  ],
  "actions": [
    {
      "description": "Governor Vetoed",
      "date": "2026-05-28",
      "organization_id": "~{\"classification\": \"executive\"}",
      "classification": [
        "executive-veto"
      ],
      "related_entities": [],
      "_processing": {
        "log_file_created": "2026-07-15T13:54:59Z"
      }
    },
    {
      "description": "Sent to the Governor",
      "date": "2026-05-19",
      "organization_id": "~{\"classification\": \"executive\"}",
      "classification": [
        "executive-receipt"
      ],
      "related_entities": [],
      "_processing": {
        "log_file_created": "2026-07-15T13:54:59Z"
      }
    },
    {
      "description": "Signed by the President of the Senate",
      "date": "2026-05-19",
      "organization_id": "~{\"classification\": \"upper\"}",
      "classification": [
        "passage"
      ],
      "related_entities": [],
      "_processing": {
        "log_file_created": "2026-07-15T13:54:59Z"
      }
    },
    {
      "description": "Signed by the Speaker of the House",
      "date": "2026-05-19",
      "organization_id": "~{\"classification\": \"lower\"}",
      "classification": [
        "passage"
      ],
      "related_entities": [],
      "_processing": {
        "log_file_created": "2026-07-15T13:54:59Z"
      }
    },
    {
      "description": "House Considered Senate Amendments - Result was to Concur - Repass",
      "date": "2026-05-13",
      "organization_id": "~{\"classification\": \"lower\"}",
      "classification": [],
      "related_entities": [],
      "_processing": {
        "log_file_created": "2026-07-15T13:54:59Z"
      }
    },
    {
      "description": "Senate Third Reading Passed - No Amendments",
      "date": "2026-05-13",
      "organization_id": "~{\"classification\": \"upper\"}",
      "classification": [
        "passage",
        "reading-3"
      ],
      "related_entities": [],
      "_processing": {
        "log_file_created": "2026-07-15T13:54:59Z"
      }
    },
    {
      "description": "Senate Second Reading Special Order - Passed with Amendments - Committee, Floor",
      "date": "2026-05-12",
      "organization_id": "~{\"classification\": \"upper\"}",
      "classification": [],
      "related_entities": [],
      "_processing": {
        "log_file_created": "2026-07-15T13:54:59Z"
      }
    },
    {
      "description": "Senate Committee on Appropriations Refer Amended to Senate Committee of the Whole",
      "date": "2026-05-11",
      "organization_id": "~{\"classification\": \"upper\"}",
      "classification": [
        "committee-passage",
        "referral-committee"
      ],
      "related_entities": [
        {
          "name": "Senate Committee of the Whole",
          "entity_type": "organization",
          "organization_id": null
        },
        {
          "name": "Appropriations",
          "entity_type": "organization",
          "organization_id": null
        }
      ],
      "_processing": {
        "log_file_created": "2026-07-15T13:54:59Z"
      }
    },
    {
      "description": "Senate Committee on Finance Refer Amended to Appropriations",
      "date": "2026-05-11",
      "organization_id": "~{\"classification\": \"upper\"}",
      "classification": [
        "referral-committee"
      ],
      "related_entities": [
        {
          "name": "Appropriations",
          "entity_type": "organization",
          "organization_id": null
        },
        {
          "name": "Finance",
          "entity_type": "organization",
          "organization_id": null
        }
      ],
      "_processing": {
        "log_file_created": "2026-07-15T13:54:59Z"
      }
    },
    {
      "description": "Introduced In Senate - Assigned to Finance",
      "date": "2026-05-08",
      "organization_id": "~{\"classification\": \"upper\"}",
      "classification": [
        "introduction"
      ],
      "related_entities": [
        {
          "name": "Finance",
          "entity_type": "organization",
          "organization_id": null
        }
      ],
      "_processing": {
        "log_file_created": "2026-07-15T13:54:59Z"
      }
    },
    {
      "description": "House Third Reading Passed with Amendments - Floor",
      "date": "2026-05-07",
      "organization_id": "~{\"classification\": \"lower\"}",
      "classification": [
        "passage",
        "reading-3"
      ],
      "related_entities": [],
      "_processing": {
        "log_file_created": "2026-07-15T13:54:59Z"
      }
    },
    {
      "description": "House Second Reading Special Order - Passed with Amendments - Committee, Floor",
      "date": "2026-05-06",
      "organization_id": "~{\"classification\": \"lower\"}",
      "classification": [],
      "related_entities": [],
      "_processing": {
        "log_file_created": "2026-07-15T13:54:59Z"
      }
    },
    {
      "description": "House Committee on Appropriations Refer Amended to House Committee of the Whole",
      "date": "2026-05-06",
      "organization_id": "~{\"classification\": \"lower\"}",
      "classification": [
        "committee-passage",
        "referral-committee"
      ],
      "related_entities": [
        {
          "name": "House Committee of the Whole",
          "entity_type": "organization",
          "organization_id": null
        },
        {
          "name": "Appropriations",
          "entity_type": "organization",
          "organization_id": null
        }
      ],
      "_processing": {
        "log_file_created": "2026-07-15T13:54:59Z"
      }
    },
    {
      "description": "House Committee on Finance Refer Amended to Appropriations",
      "date": "2026-04-27",
      "organization_id": "~{\"classification\": \"lower\"}",
      "classification": [
        "referral-committee"
      ],
      "related_entities": [
        {
          "name": "Appropriations",
          "entity_type": "organization",
          "organization_id": null
        },
        {
          "name": "Finance",
          "entity_type": "organization",
          "organization_id": null
        }
      ],
      "_processing": {
        "log_file_created": "2026-07-15T13:54:59Z"
      }
    },
    {
      "description": "Introduced In House - Assigned to Finance",
      "date": "2026-04-20",
      "organization_id": "~{\"classification\": \"lower\"}",
      "classification": [
        "introduction"
      ],
      "related_entities": [
        {
          "name": "Finance",
          "entity_type": "organization",
          "organization_id": null
        }
      ],
      "_processing": {
        "log_file_created": "2026-07-13T06:02:08Z"
      }
    }
  ],
  "sponsorships": [
    {
      "name": "S. Camacho",
      "classification": "sponsor",
      "entity_type": "person",
      "primary": true,
      "person_id": "~{\"chamber\": \"lower\", \"name\": \" S. Camacho\"}",
      "organization_id": null
    },
    {
      "name": "Y. Zokaie",
      "classification": "sponsor",
      "entity_type": "person",
      "primary": true,
      "person_id": "~{\"chamber\": \"lower\", \"name\": \" Y. Zokaie\"}",
      "organization_id": null
    },
    {
      "name": "J. Amabile",
      "classification": "sponsor",
      "entity_type": "person",
      "primary": true,
      "person_id": "~{\"chamber\": \"upper\", \"name\": \" J. Amabile\"}",
      "organization_id": null
    },
    {
      "name": "D. Roberts",
      "classification": "sponsor",
      "entity_type": "person",
      "primary": true,
      "person_id": "~{\"chamber\": \"upper\", \"name\": \" D. Roberts\"}",
      "organization_id": null
    },
    {
      "name": "J. Bacon",
      "classification": "cosponsor",
      "entity_type": "person",
      "primary": false,
      "person_id": "~{\"chamber\": \"lower\", \"name\": \" J. Bacon\"}",
      "organization_id": null
    },
    {
      "name": "M. Duran",
      "classification": "cosponsor",
      "entity_type": "person",
      "primary": false,
      "person_id": "~{\"chamber\": \"lower\", \"name\": \" M. Duran\"}",
      "organization_id": null
    },
    {
      "name": "L. Gilchrist",
      "classification": "cosponsor",
      "entity_type": "person",
      "primary": false,
      "person_id": "~{\"chamber\": \"lower\", \"name\": \" L. Gilchrist\"}",
      "organization_id": null
    },
    {
      "name": "L. Goldstein",
      "classification": "cosponsor",
      "entity_type": "person",
      "primary": false,
      "person_id": "~{\"chamber\": \"lower\", \"name\": \" L. Goldstein\"}",
      "organization_id": null
    },
    {
      "name": "J. Jackson",
      "classification": "cosponsor",
      "entity_type": "person",
      "primary": false,
      "person_id": "~{\"chamber\": \"lower\", \"name\": \" J. Jackson\"}",
      "organization_id": null
    },
    {
      "name": "M. Lindsay",
      "classification": "cosponsor",
      "entity_type": "person",
      "primary": false,
      "person_id": "~{\"chamber\": \"lower\", \"name\": \" M. Lindsay\"}",
      "organization_id": null
    },
    {
      "name": "J. Mabrey",
      "classification": "cosponsor",
      "entity_type": "person",
      "primary": false,
      "person_id": "~{\"chamber\": \"lower\", \"name\": \" J. Mabrey\"}",
      "organization_id": null
    },
    {
      "name": "K. McCormick",
      "classification": "cosponsor",
      "entity_type": "person",
      "primary": false,
      "person_id": "~{\"chamber\": \"lower\", \"name\": \" K. McCormick\"}",
      "organization_id": null
    },
    {
      "name": "K. Nguyen",
      "classification": "cosponsor",
      "entity_type": "person",
      "primary": false,
      "person_id": "~{\"chamber\": \"lower\", \"name\": \" K. Nguyen\"}",
      "organization_id": null
    },
    {
      "name": "N. Ricks",
      "classification": "cosponsor",
      "entity_type": "person",
      "primary": false,
      "person_id": "~{\"chamber\": \"lower\", \"name\": \" N. Ricks\"}",
      "organization_id": null
    },
    {
      "name": "G. Rydin",
      "classification": "cosponsor",
      "entity_type": "person",
      "primary": false,
      "person_id": "~{\"chamber\": \"lower\", \"name\": \" G. Rydin\"}",
      "organization_id": null
    },
    {
      "name": "J. Coleman",
      "classification": "cosponsor",
      "entity_type": "person",
      "primary": false,
      "person_id": "~{\"chamber\": \"upper\", \"name\": \" J. Coleman\"}",
      "organization_id": null
    },
    {
      "name": "L. Cutter",
      "classification": "cosponsor",
      "entity_type": "person",
      "primary": false,
      "person_id": "~{\"chamber\": \"upper\", \"name\": \" L. Cutter\"}",
      "organization_id": null
    },
    {
      "name": "J. Gonzales",
      "classification": "cosponsor",
      "entity_type": "person",
      "primary": false,
      "person_id": "~{\"chamber\": \"upper\", \"name\": \" J. Gonzales\"}",
      "organization_id": null
    },
    {
      "name": "I. Jodeh",
      "classification": "cosponsor",
      "entity_type": "person",
      "primary": false,
      "person_id": "~{\"chamber\": \"upper\", \"name\": \" I. Jodeh\"}",
      "organization_id": null
    },
    {
      "name": "C. Kipp",
      "classification": "cosponsor",
      "entity_type": "person",
      "primary": false,
      "person_id": "~{\"chamber\": \"upper\", \"name\": \" C. Kipp\"}",
      "organization_id": null
    },
    {
      "name": "C. Kolker",
      "classification": "cosponsor",
      "entity_type": "person",
      "primary": false,
      "person_id": "~{\"chamber\": \"upper\", \"name\": \" C. Kolker\"}",
      "organization_id": null
    },
    {
      "name": "K. Wallace",
      "classification": "cosponsor",
      "entity_type": "person",
      "primary": false,
      "person_id": "~{\"chamber\": \"upper\", \"name\": \" K. Wallace\"}",
      "organization_id": null
    }
  ],
  "related_bills": [],
  "versions": [
    {
      "note": "Signed Act",
      "links": [
        {
          "url": "https://leg.colorado.gov/bill_files/116900/download",
          "media_type": "application/pdf"
        }
      ],
      "date": "2026-06-01",
      "classification": ""
    },
    {
      "note": "Final Act",
      "links": [
        {
          "url": "https://leg.colorado.gov/bill_files/116498/download",
          "media_type": "application/pdf"
        }
      ],
      "date": "2026-05-18",
      "classification": ""
    },
    {
      "note": "Rerevised",
      "links": [
        {
          "url": "https://leg.colorado.gov/bill_files/116476/download",
          "media_type": "application/pdf"
        }
      ],
      "date": "2026-05-13",
      "classification": ""
    },
    {
      "note": "Revised",
      "links": [
        {
          "url": "https://leg.colorado.gov/bill_files/116397/download",
          "media_type": "application/pdf"
        }
      ],
      "date": "2026-05-12",
      "classification": ""
    },
    {
      "note": "Reengrossed",
      "links": [
        {
          "url": "https://leg.colorado.gov/bill_files/116086/download",
          "media_type": "application/pdf"
        }
      ],
      "date": "2026-05-07",
      "classification": ""
    },
    {
      "note": "Engrossed",
      "links": [
        {
          "url": "https://leg.colorado.gov/bill_files/115959/download",
          "media_type": "application/pdf"
        }
      ],
      "date": "2026-05-06",
      "classification": ""
    },
    {
      "note": "Introduced",
      "links": [
        {
          "url": "https://leg.colorado.gov/bill_files/114914/download",
          "media_type": "application/pdf"
        }
      ],
      "date": "2026-04-20",
      "classification": ""
    }
  ],
  "documents": [
    {
      "note": "Amendment L.033",
      "links": [
        {
          "url": "https://leg.colorado.gov/bill_amendments/20310/download",
          "media_type": "application/pdf"
        }
      ],
      "date": "2026-05-12",
      "classification": ""
    },
    {
      "note": "Amendment J.002",
      "links": [
        {
          "url": "https://leg.colorado.gov/bill_amendments/20296/download",
          "media_type": "application/pdf"
        }
      ],
      "date": "2026-05-11",
      "classification": ""
    },
    {
      "note": "Amendment L.032",
      "links": [
        {
          "url": "https://leg.colorado.gov/bill_amendments/20277/download",
          "media_type": "application/pdf"
        }
      ],
      "date": "2026-05-11",
      "classification": ""
    },
    {
      "note": "Amendment L.030",
      "links": [
        {
          "url": "https://leg.colorado.gov/bill_amendments/20074/download",
          "media_type": "application/pdf"
        }
      ],
      "date": "2026-05-07",
      "classification": ""
    },
    {
      "note": "Amendment L.026",
      "links": [
        {
          "url": "https://leg.colorado.gov/bill_amendments/19998/download",
          "media_type": "application/pdf"
        }
      ],
      "date": "2026-05-06",
      "classification": ""
    },
    {
      "note": "Amendment L.027",
      "links": [
        {
          "url": "https://leg.colorado.gov/bill_amendments/19999/download",
          "media_type": "application/pdf"
        }
      ],
      "date": "2026-05-06",
      "classification": ""
    },
    {
      "note": "Amendment L.025",
      "links": [
        {
          "url": "https://leg.colorado.gov/bill_amendments/20000/download",
          "media_type": "application/pdf"
        }
      ],
      "date": "2026-05-06",
      "classification": ""
    },
    {
      "note": "Amendment J.001",
      "links": [
        {
          "url": "https://leg.colorado.gov/bill_amendments/19976/download",
          "media_type": "application/pdf"
        }
      ],
      "date": "2026-05-06",
      "classification": ""
    },
    {
      "note": "Amendment L.019",
      "links": [
        {
          "url": "https://leg.colorado.gov/bill_amendments/19977/download",
          "media_type": "application/pdf"
        }
      ],
      "date": "2026-05-06",
      "classification": ""
    },
    {
      "note": "Amendment L.018",
      "links": [
        {
          "url": "https://leg.colorado.gov/bill_amendments/19978/download",
          "media_type": "application/pdf"
        }
      ],
      "date": "2026-05-06",
      "classification": ""
    },
    {
      "note": "Amendment L.017",
      "links": [
        {
          "url": "https://leg.colorado.gov/bill_amendments/19979/download",
          "media_type": "application/pdf"
        }
      ],
      "date": "2026-05-06",
      "classification": ""
    },
    {
      "note": "Amendment L.008",
      "links": [
        {
          "url": "https://leg.colorado.gov/bill_amendments/19621/download",
          "media_type": "application/pdf"
        }
      ],
      "date": "2026-04-27",
      "classification": ""
    },
    {
      "note": "Amendment L.009",
      "links": [
        {
          "url": "https://leg.colorado.gov/bill_amendments/19615/download",
          "media_type": "application/pdf"
        }
      ],
      "date": "2026-04-27",
      "classification": ""
    },
    {
      "note": "Amendment L.005",
      "links": [
        {
          "url": "https://leg.colorado.gov/bill_amendments/19616/download",
          "media_type": "application/pdf"
        }
      ],
      "date": "2026-04-27",
      "classification": ""
    },
    {
      "note": "Amendment L.004",
      "links": [
        {
          "url": "https://leg.colorado.gov/bill_amendments/19617/download",
          "media_type": "application/pdf"
        }
      ],
      "date": "2026-04-27",
      "classification": ""
    },
    {
      "note": "Amendment L.006",
      "links": [
        {
          "url": "https://leg.colorado.gov/bill_amendments/19618/download",
          "media_type": "application/pdf"
        }
      ],
      "date": "2026-04-27",
      "classification": ""
    },
    {
      "note": "Amendment L.001",
      "links": [
        {
          "url": "https://leg.colorado.gov/bill_amendments/19619/download",
          "media_type": "application/pdf"
        }
      ],
      "date": "2026-04-27",
      "classification": ""
    },
    {
      "note": "Amendment L.007",
      "links": [
        {
          "url": "https://leg.colorado.gov/bill_amendments/19620/download",
          "media_type": "application/pdf"
        }
      ],
      "date": "2026-04-27",
      "classification": ""
    },
    {
      "note": "Amendment L.003",
      "links": [
        {
          "url": "https://leg.colorado.gov/bill_amendments/19611/download",
          "media_type": "application/pdf"
        }
      ],
      "date": "2026-04-27",
      "classification": ""
    },
    {
      "note": "Amendment L.002",
      "links": [
        {
          "url": "https://leg.colorado.gov/bill_amendments/19612/download",
          "media_type": "application/pdf"
        }
      ],
      "date": "2026-04-27",
      "classification": ""
    },
    {
      "note": "Amendment L.013",
      "links": [
        {
          "url": "https://leg.colorado.gov/bill_amendments/19613/download",
          "media_type": "application/pdf"
        }
      ],
      "date": "2026-04-27",
      "classification": ""
    },
    {
      "note": "Amendment L.012",
      "links": [
        {
          "url": "https://leg.colorado.gov/bill_amendments/19614/download",
          "media_type": "application/pdf"
        }
      ],
      "date": "2026-04-27",
      "classification": ""
    },
    {
      "note": "Committee Report for Appropriations on 05/11/2026",
      "links": [
        {
          "url": "https://s3.us-west-2.amazonaws.com/beta.leg.colorado.gov/dcfff9e2aad516095241ca43c03fed92",
          "media_type": "text/html"
        }
      ],
      "date": "",
      "classification": "committee-report"
    },
    {
      "note": "Committee Report for Finance on 05/11/2026",
      "links": [
        {
          "url": "https://s3.us-west-2.amazonaws.com/beta.leg.colorado.gov/975e57d70f2cb607baf9bd5555ca7481",
          "media_type": "text/html"
        }
      ],
      "date": "",
      "classification": "committee-report"
    },
    {
      "note": "Committee Report for Appropriations on 05/06/2026",
      "links": [
        {
          "url": "https://s3.us-west-2.amazonaws.com/beta.leg.colorado.gov/7a3bb0ad02143606282da6529b3db7d3",
          "media_type": "text/html"
        }
      ],
      "date": "",
      "classification": "committee-report"
    },
    {
      "note": "Committee Report for Finance on 04/27/2026",
      "links": [
        {
          "url": "https://s3.us-west-2.amazonaws.com/beta.leg.colorado.gov/aff2b6aece481ee9365038f8da5d9f1f",
          "media_type": "text/html"
        }
      ],
      "date": "",
      "classification": "committee-report"
    },
    {
      "note": "Third Revised Fiscal Note",
      "links": [
        {
          "url": "https://leg.colorado.gov/bill_files/116345/download",
          "media_type": "application/pdf"
        }
      ],
      "date": "2026-05-11",
      "classification": "fiscal-note"
    },
    {
      "note": "Second Revised Fiscal Note",
      "links": [
        {
          "url": "https://leg.colorado.gov/bill_files/116218/download",
          "media_type": "application/pdf"
        }
      ],
      "date": "2026-05-09",
      "classification": "fiscal-note"
    },
    {
      "note": "First Revised Fiscal Note",
      "links": [
        {
          "url": "https://leg.colorado.gov/bill_files/115856/download",
          "media_type": "application/pdf"
        }
      ],
      "date": "2026-05-05",
      "classification": "fiscal-note"
    },
    {
      "note": "Initial Fiscal Note",
      "links": [
        {
          "url": "https://leg.colorado.gov/bill_files/115139/download",
          "media_type": "application/pdf"
        }
      ],
      "date": "2026-04-23",
      "classification": "fiscal-note"
    }
  ],
  "citations": [],
  "sources": [
    {
      "url": "https://leg.colorado.gov/bills/HB26-1418",
      "note": ""
    }
  ],
  "extras": {},
  "jurisdiction": {
    "id": "ocd-jurisdiction/country:us/state:co/government",
    "name": "Colorado",
    "classification": "state",
    "division_id": "ocd-division/country:us/state:co"
  },
  "_processing": {
    "logs_latest_update": "2026-07-15T13:54:59Z",
    "text_extraction_latest_update": "2026-07-13T06:50:21.119553Z"
  }
}