{
  "legislative_session": "2026A",
  "identifier": "SB 048",
  "title": "Remove Exception to Marry with Judicial Approval",
  "from_organization": "~{\"classification\": \"upper\"}",
  "classification": [
    "bill"
  ],
  "subject": [
    "Children & Domestic Matters"
  ],
  "abstracts": [],
  "other_titles": [],
  "other_identifiers": [
    {
      "identifier": "ocd-bill-co-2026a-sb48"
    }
  ],
  "actions": [
    {
      "description": "Introduced In Senate - Assigned to State, Veterans, & Military Affairs",
      "date": "2026-01-27",
      "organization_id": "~{\"classification\": \"upper\"}",
      "classification": [
        "introduction"
      ],
      "related_entities": [
        {
          "name": "State, Veterans, & Military Affairs",
          "entity_type": "organization",
          "organization_id": null
        }
      ],
      "_processing": {
        "log_file_created": "2026-07-13T06:02:08Z"
      }
    }
  ],
  "sponsorships": [
    {
      "name": "N. Hinrichsen",
      "classification": "sponsor",
      "entity_type": "person",
      "primary": true,
      "person_id": "~{\"chamber\": \"upper\", \"name\": \" N. Hinrichsen\"}",
      "organization_id": null
    },
    {
      "name": "J. Marchman",
      "classification": "sponsor",
      "entity_type": "person",
      "primary": true,
      "person_id": "~{\"chamber\": \"upper\", \"name\": \" J. Marchman\"}",
      "organization_id": null
    },
    {
      "name": "J. Joseph",
      "classification": "sponsor",
      "entity_type": "person",
      "primary": true,
      "person_id": "~{\"chamber\": \"lower\", \"name\": \" J. Joseph\"}",
      "organization_id": null
    }
  ],
  "related_bills": [],
  "versions": [
    {
      "note": "Introduced",
      "links": [
        {
          "url": "https://leg.colorado.gov/bill_files/110974/download",
          "media_type": "application/pdf"
        },
        {
          "url": "https://s3.us-west-2.amazonaws.com/beta.leg.colorado.gov/1f4d02d8a1f7717299737df09d255aff",
          "media_type": "text/html"
        }
      ],
      "date": "2026-01-27",
      "classification": ""
    }
  ],
  "documents": [],
  "citations": [],
  "sources": [
    {
      "url": "https://leg.colorado.gov/bills/SB26-048",
      "note": ""
    }
  ],
  "extras": {},
  "jurisdiction": {
    "id": "ocd-jurisdiction/country:us/state:co/government",
    "name": "Colorado",
    "classification": "state",
    "division_id": "ocd-division/country:us/state:co"
  },
  "_processing": {
    "logs_latest_update": "2026-07-13T06:02:08Z",
    "text_extraction_latest_update": "2026-07-13T06:44:51.054967Z"
  }
}