{
  "legislative_session": "2026A",
  "identifier": "SB 017",
  "title": "Out-of-Network Health Insurance Dispute Resolution",
  "from_organization": "~{\"classification\": \"upper\"}",
  "classification": [
    "bill"
  ],
  "subject": [
    "Insurance"
  ],
  "abstracts": [
    {
      "note": "summary",
      "abstract": "The bill makes changes to the dispute resolution process between health insurance carriers (carriers) and out-of-network health-care providers (providers) by:Mandating that a carrier provide a remittance advice with each payment made to a provider;Establishing penalties that the division of insurance (division) may assess against a carrier that fails to properly reimburse a provider for services provided to a patient;Requiring a carrier to annually submit information to the division concerning patient use of out-of-network providers; andRequiring the division to produce an annual report regarding patient use of out-of-network providers and relevant arbitration data and statistics.(Note: This summary applies to this bill as introduced.)"
    }
  ],
  "other_titles": [],
  "other_identifiers": [
    {
      "identifier": "ocd-bill-co-2026a-sb17"
    }
  ],
  "actions": [
    {
      "description": "Introduced In Senate - Assigned to Health & Human Services",
      "date": "2026-01-14",
      "organization_id": "~{\"classification\": \"upper\"}",
      "classification": [
        "introduction"
      ],
      "related_entities": [
        {
          "name": "Health & Human Services",
          "entity_type": "organization",
          "organization_id": null
        }
      ],
      "_processing": {
        "log_file_created": "2026-07-13T06:02:08Z"
      }
    }
  ],
  "sponsorships": [
    {
      "name": "S. Bright",
      "classification": "sponsor",
      "entity_type": "person",
      "primary": true,
      "person_id": "~{\"chamber\": \"upper\", \"name\": \" S. Bright\"}",
      "organization_id": null
    },
    {
      "name": "L. Daugherty",
      "classification": "sponsor",
      "entity_type": "person",
      "primary": true,
      "person_id": "~{\"chamber\": \"upper\", \"name\": \" L. Daugherty\"}",
      "organization_id": null
    }
  ],
  "related_bills": [],
  "versions": [
    {
      "note": "Introduced",
      "links": [
        {
          "url": "https://s3.us-west-2.amazonaws.com/beta.leg.colorado.gov/3c3cd87c742adf2574e4bd2af97a65e5",
          "media_type": "application/pdf"
        },
        {
          "url": "https://s3.us-west-2.amazonaws.com/beta.leg.colorado.gov/389643ed88fd51e17b57fb79eb437ec0",
          "media_type": "text/html"
        }
      ],
      "date": "2026-01-14",
      "classification": ""
    }
  ],
  "documents": [],
  "citations": [],
  "sources": [
    {
      "url": "https://leg.colorado.gov/bills/SB26-017",
      "note": ""
    }
  ],
  "extras": {},
  "jurisdiction": {
    "id": "ocd-jurisdiction/country:us/state:co/government",
    "name": "Colorado",
    "classification": "state",
    "division_id": "ocd-division/country:us/state:co"
  },
  "_processing": {
    "logs_latest_update": "2026-07-13T06:02:08Z",
    "text_extraction_latest_update": "2026-07-13T06:29:34.659213Z"
  }
}