{
  "legislative_session": "2026A",
  "identifier": "SJR 020",
  "title": "Recognize Home Education Day",
  "from_organization": "~{\"classification\": \"upper\"}",
  "classification": [
    "bill"
  ],
  "subject": [
    "General Assembly"
  ],
  "abstracts": [],
  "other_titles": [],
  "other_identifiers": [
    {
      "identifier": "ocd-bill-co-2026a-sjr20"
    }
  ],
  "actions": [
    {
      "description": "Senate Third Reading Passed - No Amendments",
      "date": "2026-04-09",
      "organization_id": "~{\"classification\": \"upper\"}",
      "classification": [
        "passage",
        "reading-3"
      ],
      "related_entities": [],
      "_processing": {
        "log_file_created": "2026-07-13T06:02:08Z"
      }
    },
    {
      "description": "Senate Third Reading Laid Over to 04/09/2026 - No Amendments",
      "date": "2026-04-06",
      "organization_id": "~{\"classification\": \"upper\"}",
      "classification": [],
      "related_entities": [],
      "_processing": {
        "log_file_created": "2026-07-13T06:02:08Z"
      }
    },
    {
      "description": "Introduced In Senate - Assigned to",
      "date": "2026-04-06",
      "organization_id": "~{\"classification\": \"upper\"}",
      "classification": [
        "introduction"
      ],
      "related_entities": [],
      "_processing": {
        "log_file_created": "2026-07-13T06:02:08Z"
      }
    }
  ],
  "sponsorships": [
    {
      "name": "R. Pelton",
      "classification": "sponsor",
      "entity_type": "person",
      "primary": true,
      "person_id": "~{\"chamber\": \"upper\", \"name\": \" R. Pelton\"}",
      "organization_id": null
    },
    {
      "name": "L. Garcia Sander",
      "classification": "sponsor",
      "entity_type": "person",
      "primary": true,
      "person_id": "~{\"chamber\": \"lower\", \"name\": \" L. Garcia Sander\"}",
      "organization_id": null
    },
    {
      "name": "D. Johnson",
      "classification": "sponsor",
      "entity_type": "person",
      "primary": true,
      "person_id": "~{\"chamber\": \"lower\", \"name\": \" D. Johnson\"}",
      "organization_id": null
    },
    {
      "name": "J. Amabile",
      "classification": "cosponsor",
      "entity_type": "person",
      "primary": false,
      "person_id": "~{\"chamber\": \"upper\", \"name\": \" J. Amabile\"}",
      "organization_id": null
    },
    {
      "name": "M. Baisley",
      "classification": "cosponsor",
      "entity_type": "person",
      "primary": false,
      "person_id": "~{\"chamber\": \"upper\", \"name\": \" M. Baisley\"}",
      "organization_id": null
    },
    {
      "name": "A. Benavidez",
      "classification": "cosponsor",
      "entity_type": "person",
      "primary": false,
      "person_id": "~{\"chamber\": \"upper\", \"name\": \" A. Benavidez\"}",
      "organization_id": null
    },
    {
      "name": "J. Bridges",
      "classification": "cosponsor",
      "entity_type": "person",
      "primary": false,
      "person_id": "~{\"chamber\": \"upper\", \"name\": \" J. Bridges\"}",
      "organization_id": null
    },
    {
      "name": "S. Bright",
      "classification": "cosponsor",
      "entity_type": "person",
      "primary": false,
      "person_id": "~{\"chamber\": \"upper\", \"name\": \" S. Bright\"}",
      "organization_id": null
    },
    {
      "name": "J. Carson",
      "classification": "cosponsor",
      "entity_type": "person",
      "primary": false,
      "person_id": "~{\"chamber\": \"upper\", \"name\": \" J. Carson\"}",
      "organization_id": null
    },
    {
      "name": "M. Catlin",
      "classification": "cosponsor",
      "entity_type": "person",
      "primary": false,
      "person_id": "~{\"chamber\": \"upper\", \"name\": \" M. Catlin\"}",
      "organization_id": null
    },
    {
      "name": "J. Coleman",
      "classification": "cosponsor",
      "entity_type": "person",
      "primary": false,
      "person_id": "~{\"chamber\": \"upper\", \"name\": \" J. Coleman\"}",
      "organization_id": null
    },
    {
      "name": "J. Danielson",
      "classification": "cosponsor",
      "entity_type": "person",
      "primary": false,
      "person_id": "~{\"chamber\": \"upper\", \"name\": \" J. Danielson\"}",
      "organization_id": null
    },
    {
      "name": "L. Daugherty",
      "classification": "cosponsor",
      "entity_type": "person",
      "primary": false,
      "person_id": "~{\"chamber\": \"upper\", \"name\": \" L. Daugherty\"}",
      "organization_id": null
    },
    {
      "name": "T. Exum",
      "classification": "cosponsor",
      "entity_type": "person",
      "primary": false,
      "person_id": "~{\"chamber\": \"upper\", \"name\": \" T. Exum\"}",
      "organization_id": null
    },
    {
      "name": "L. Frizell",
      "classification": "cosponsor",
      "entity_type": "person",
      "primary": false,
      "person_id": "~{\"chamber\": \"upper\", \"name\": \" L. Frizell\"}",
      "organization_id": null
    },
    {
      "name": "N. Hinrichsen",
      "classification": "cosponsor",
      "entity_type": "person",
      "primary": false,
      "person_id": "~{\"chamber\": \"upper\", \"name\": \" N. Hinrichsen\"}",
      "organization_id": null
    },
    {
      "name": "I. Jodeh",
      "classification": "cosponsor",
      "entity_type": "person",
      "primary": false,
      "person_id": "~{\"chamber\": \"upper\", \"name\": \" I. Jodeh\"}",
      "organization_id": null
    },
    {
      "name": "C. Kipp",
      "classification": "cosponsor",
      "entity_type": "person",
      "primary": false,
      "person_id": "~{\"chamber\": \"upper\", \"name\": \" C. Kipp\"}",
      "organization_id": null
    },
    {
      "name": "C. Kolker",
      "classification": "cosponsor",
      "entity_type": "person",
      "primary": false,
      "person_id": "~{\"chamber\": \"upper\", \"name\": \" C. Kolker\"}",
      "organization_id": null
    },
    {
      "name": "W. Lindstedt",
      "classification": "cosponsor",
      "entity_type": "person",
      "primary": false,
      "person_id": "~{\"chamber\": \"upper\", \"name\": \" W. Lindstedt\"}",
      "organization_id": null
    },
    {
      "name": "J. Marchman",
      "classification": "cosponsor",
      "entity_type": "person",
      "primary": false,
      "person_id": "~{\"chamber\": \"upper\", \"name\": \" J. Marchman\"}",
      "organization_id": null
    },
    {
      "name": "K. Mullica",
      "classification": "cosponsor",
      "entity_type": "person",
      "primary": false,
      "person_id": "~{\"chamber\": \"upper\", \"name\": \" K. Mullica\"}",
      "organization_id": null
    },
    {
      "name": "B. Pelton",
      "classification": "cosponsor",
      "entity_type": "person",
      "primary": false,
      "person_id": "~{\"chamber\": \"upper\", \"name\": \" B. Pelton\"}",
      "organization_id": null
    },
    {
      "name": "J. Rich",
      "classification": "cosponsor",
      "entity_type": "person",
      "primary": false,
      "person_id": "~{\"chamber\": \"upper\", \"name\": \" J. Rich\"}",
      "organization_id": null
    },
    {
      "name": "D. Roberts",
      "classification": "cosponsor",
      "entity_type": "person",
      "primary": false,
      "person_id": "~{\"chamber\": \"upper\", \"name\": \" D. Roberts\"}",
      "organization_id": null
    },
    {
      "name": "R. Rodriguez",
      "classification": "cosponsor",
      "entity_type": "person",
      "primary": false,
      "person_id": "~{\"chamber\": \"upper\", \"name\": \" R. Rodriguez\"}",
      "organization_id": null
    },
    {
      "name": "C. Simpson",
      "classification": "cosponsor",
      "entity_type": "person",
      "primary": false,
      "person_id": "~{\"chamber\": \"upper\", \"name\": \" C. Simpson\"}",
      "organization_id": null
    },
    {
      "name": "M. Snyder",
      "classification": "cosponsor",
      "entity_type": "person",
      "primary": false,
      "person_id": "~{\"chamber\": \"upper\", \"name\": \" M. Snyder\"}",
      "organization_id": null
    },
    {
      "name": "T. Sullivan",
      "classification": "cosponsor",
      "entity_type": "person",
      "primary": false,
      "person_id": "~{\"chamber\": \"upper\", \"name\": \" T. Sullivan\"}",
      "organization_id": null
    },
    {
      "name": "K. Wallace",
      "classification": "cosponsor",
      "entity_type": "person",
      "primary": false,
      "person_id": "~{\"chamber\": \"upper\", \"name\": \" K. Wallace\"}",
      "organization_id": null
    },
    {
      "name": "M. Weissman",
      "classification": "cosponsor",
      "entity_type": "person",
      "primary": false,
      "person_id": "~{\"chamber\": \"upper\", \"name\": \" M. Weissman\"}",
      "organization_id": null
    },
    {
      "name": "L. Zamora Wilson",
      "classification": "cosponsor",
      "entity_type": "person",
      "primary": false,
      "person_id": "~{\"chamber\": \"upper\", \"name\": \" L. Zamora Wilson\"}",
      "organization_id": null
    }
  ],
  "related_bills": [],
  "versions": [
    {
      "note": "Engrossed",
      "links": [
        {
          "url": "https://leg.colorado.gov/bill_files/114285/download",
          "media_type": "application/pdf"
        }
      ],
      "date": "2026-04-09",
      "classification": ""
    },
    {
      "note": "Introduced",
      "links": [
        {
          "url": "https://leg.colorado.gov/bill_files/114283/download",
          "media_type": "application/pdf"
        }
      ],
      "date": "2026-04-06",
      "classification": ""
    }
  ],
  "documents": [],
  "citations": [],
  "sources": [
    {
      "url": "https://leg.colorado.gov/bills/SJR26-020",
      "note": ""
    }
  ],
  "extras": {},
  "jurisdiction": {
    "id": "ocd-jurisdiction/country:us/state:co/government",
    "name": "Colorado",
    "classification": "state",
    "division_id": "ocd-division/country:us/state:co"
  },
  "_processing": {
    "logs_latest_update": "2026-07-13T06:02:08Z",
    "text_extraction_latest_update": "2026-07-13T06:28:17.115643Z"
  }
}