{
  "legislative_session": "2026A",
  "identifier": "HB 1125",
  "title": "Parent Penalties Minor Using Electric Bicycle",
  "from_organization": "~{\"classification\": \"lower\"}",
  "classification": [
    "bill"
  ],
  "subject": [
    "Transportation & Motor Vehicles"
  ],
  "abstracts": [
    {
      "note": "summary",
      "abstract": "The bill creates penalties to be assessed against a parent or guardian who permits their minor child or ward to operate an electrical assisted bicycle, electric motorcycle, electric scooter, or electric skateboard (electric vehicle) if the minor child or ward operates the electric vehicle in a manner that violates certain laws concerning the usage of such electric vehicles, including laws regarding age requirements for different classes of such electric vehicles, how to safely and properly operate such electric vehicles on roadways or pathways, and required safety gear.(Note: This summary applies to this bill as introduced.)"
    }
  ],
  "other_titles": [],
  "other_identifiers": [
    {
      "identifier": "ocd-bill-co-2026a-hb1125"
    }
  ],
  "actions": [
    {
      "description": "House Committee on Transportation, Housing & Local Government Postpone Indefinitely",
      "date": "2026-03-04",
      "organization_id": "~{\"classification\": \"lower\"}",
      "classification": [],
      "related_entities": [
        {
          "name": "Transportation",
          "entity_type": "organization",
          "organization_id": null
        },
        {
          "name": "Local Government",
          "entity_type": "organization",
          "organization_id": null
        }
      ],
      "_processing": {
        "log_file_created": "2026-07-15T13:54:58Z"
      }
    },
    {
      "description": "Introduced In House - Assigned to Transportation, Housing & Local Government",
      "date": "2026-02-04",
      "organization_id": "~{\"classification\": \"lower\"}",
      "classification": [
        "introduction"
      ],
      "related_entities": [
        {
          "name": "Transportation, Housing & Local Government",
          "entity_type": "organization",
          "organization_id": null
        },
        {
          "name": "Transportation",
          "entity_type": "organization",
          "organization_id": null
        },
        {
          "name": "Local Government",
          "entity_type": "organization",
          "organization_id": null
        }
      ],
      "_processing": {
        "log_file_created": "2026-07-13T06:02:08Z"
      }
    }
  ],
  "sponsorships": [
    {
      "name": "B. Bradley",
      "classification": "sponsor",
      "entity_type": "person",
      "primary": true,
      "person_id": "~{\"chamber\": \"lower\", \"name\": \" B. Bradley\"}",
      "organization_id": null
    },
    {
      "name": "J. Carson",
      "classification": "sponsor",
      "entity_type": "person",
      "primary": true,
      "person_id": "~{\"chamber\": \"upper\", \"name\": \" J. Carson\"}",
      "organization_id": null
    }
  ],
  "related_bills": [],
  "versions": [
    {
      "note": "Introduced",
      "links": [
        {
          "url": "https://leg.colorado.gov/bill_files/111327/download",
          "media_type": "application/pdf"
        }
      ],
      "date": "2026-02-04",
      "classification": ""
    }
  ],
  "documents": [
    {
      "note": "Committee Report for Transportation, Housing & Local Government on 03/04/2026",
      "links": [
        {
          "url": "https://s3.us-west-2.amazonaws.com/beta.leg.colorado.gov/4a2aa94b426a155cf948d7bc826e0b4c",
          "media_type": "text/html"
        }
      ],
      "date": "",
      "classification": "committee-report"
    },
    {
      "note": "Final Fiscal Note",
      "links": [
        {
          "url": "https://leg.colorado.gov/bill_files/117094/download",
          "media_type": "application/pdf"
        }
      ],
      "date": "2026-06-04",
      "classification": "fiscal-note"
    },
    {
      "note": "Initial Fiscal Note",
      "links": [
        {
          "url": "https://leg.colorado.gov/bill_files/112556/download",
          "media_type": "application/pdf"
        }
      ],
      "date": "2026-02-24",
      "classification": "fiscal-note"
    }
  ],
  "citations": [],
  "sources": [
    {
      "url": "https://leg.colorado.gov/bills/HB26-1125",
      "note": ""
    }
  ],
  "extras": {},
  "jurisdiction": {
    "id": "ocd-jurisdiction/country:us/state:co/government",
    "name": "Colorado",
    "classification": "state",
    "division_id": "ocd-division/country:us/state:co"
  },
  "_processing": {
    "logs_latest_update": "2026-07-15T13:54:58Z",
    "text_extraction_latest_update": "2026-07-13T06:21:00.265207Z"
  }
}