{
  "legislative_session": "2026A",
  "identifier": "HB 1369",
  "title": "Repeal of Contract for Online Platform Use",
  "from_organization": "~{\"classification\": \"lower\"}",
  "classification": [
    "bill"
  ],
  "subject": [
    "Education & School Finance (Pre & K-12)"
  ],
  "abstracts": [],
  "other_titles": [],
  "other_identifiers": [
    {
      "identifier": "ocd-bill-co-2026a-hb1369"
    }
  ],
  "actions": [
    {
      "description": "Introduced In House - Assigned to Appropriations",
      "date": "2026-04-02",
      "organization_id": "~{\"classification\": \"lower\"}",
      "classification": [
        "introduction"
      ],
      "related_entities": [
        {
          "name": "Appropriations",
          "entity_type": "organization",
          "organization_id": null
        }
      ],
      "_processing": {
        "log_file_created": "2026-07-13T06:02:08Z"
      }
    }
  ],
  "sponsorships": [
    {
      "name": "K. Brown",
      "classification": "sponsor",
      "entity_type": "person",
      "primary": true,
      "person_id": "~{\"chamber\": \"lower\", \"name\": \" K. Brown\"}",
      "organization_id": null
    },
    {
      "name": "R. Taggart",
      "classification": "sponsor",
      "entity_type": "person",
      "primary": true,
      "person_id": "~{\"chamber\": \"lower\", \"name\": \" R. Taggart\"}",
      "organization_id": null
    },
    {
      "name": "J. Amabile",
      "classification": "sponsor",
      "entity_type": "person",
      "primary": true,
      "person_id": "~{\"chamber\": \"upper\", \"name\": \" J. Amabile\"}",
      "organization_id": null
    },
    {
      "name": "B. Kirkmeyer",
      "classification": "sponsor",
      "entity_type": "person",
      "primary": true,
      "person_id": "~{\"chamber\": \"upper\", \"name\": \" B. Kirkmeyer\"}",
      "organization_id": null
    },
    {
      "name": "E. Sirota",
      "classification": "sponsor",
      "entity_type": "person",
      "primary": true,
      "person_id": "~{\"chamber\": \"lower\", \"name\": \" E. Sirota\"}",
      "organization_id": null
    },
    {
      "name": "J. Bridges",
      "classification": "sponsor",
      "entity_type": "person",
      "primary": true,
      "person_id": "~{\"chamber\": \"upper\", \"name\": \" J. Bridges\"}",
      "organization_id": null
    }
  ],
  "related_bills": [],
  "versions": [
    {
      "note": "Introduced",
      "links": [
        {
          "url": "https://leg.colorado.gov/bill_files/114012/download",
          "media_type": "application/pdf"
        }
      ],
      "date": "2026-04-02",
      "classification": ""
    }
  ],
  "documents": [
    {
      "note": "Initial Fiscal Note",
      "links": [
        {
          "url": "https://leg.colorado.gov/bill_files/114077/download",
          "media_type": "application/pdf"
        }
      ],
      "date": "2026-04-02",
      "classification": "fiscal-note"
    }
  ],
  "citations": [],
  "sources": [
    {
      "url": "https://leg.colorado.gov/bills/HB26-1369",
      "note": ""
    }
  ],
  "extras": {},
  "jurisdiction": {
    "id": "ocd-jurisdiction/country:us/state:co/government",
    "name": "Colorado",
    "classification": "state",
    "division_id": "ocd-division/country:us/state:co"
  },
  "_processing": {
    "logs_latest_update": "2026-07-13T06:02:08Z",
    "text_extraction_latest_update": "2026-07-13T06:19:47.349141Z"
  }
}