{
  "legislative_session": "2026A",
  "identifier": "HB 1186",
  "title": "Sunset Regulation of Cash-Bonding Agents",
  "from_organization": "~{\"classification\": \"lower\"}",
  "classification": [
    "bill"
  ],
  "subject": [
    "Insurance"
  ],
  "abstracts": [],
  "other_titles": [],
  "other_identifiers": [
    {
      "identifier": "ocd-bill-co-2026a-hb1186"
    }
  ],
  "actions": [
    {
      "description": "Introduced In House - Assigned to Judiciary",
      "date": "2026-02-09",
      "organization_id": "~{\"classification\": \"lower\"}",
      "classification": [
        "introduction"
      ],
      "related_entities": [
        {
          "name": "Judiciary",
          "entity_type": "organization",
          "organization_id": null
        }
      ],
      "_processing": {
        "log_file_created": "2026-07-13T06:02:08Z"
      }
    }
  ],
  "sponsorships": [
    {
      "name": "J. Mabrey",
      "classification": "sponsor",
      "entity_type": "person",
      "primary": true,
      "person_id": "~{\"chamber\": \"lower\", \"name\": \" J. Mabrey\"}",
      "organization_id": null
    },
    {
      "name": "M. Soper",
      "classification": "sponsor",
      "entity_type": "person",
      "primary": true,
      "person_id": "~{\"chamber\": \"lower\", \"name\": \" M. Soper\"}",
      "organization_id": null
    },
    {
      "name": "M. Ball",
      "classification": "sponsor",
      "entity_type": "person",
      "primary": true,
      "person_id": "~{\"chamber\": \"upper\", \"name\": \" M. Ball\"}",
      "organization_id": null
    },
    {
      "name": "M. Weissman",
      "classification": "sponsor",
      "entity_type": "person",
      "primary": true,
      "person_id": "~{\"chamber\": \"upper\", \"name\": \" M. Weissman\"}",
      "organization_id": null
    },
    {
      "name": "M. Carter",
      "classification": "sponsor",
      "entity_type": "person",
      "primary": true,
      "person_id": "~{\"chamber\": \"lower\", \"name\": \" M. Carter\"}",
      "organization_id": null
    },
    {
      "name": "C. Clifford",
      "classification": "sponsor",
      "entity_type": "person",
      "primary": true,
      "person_id": "~{\"chamber\": \"lower\", \"name\": \" C. Clifford\"}",
      "organization_id": null
    },
    {
      "name": "C. Espenoza",
      "classification": "sponsor",
      "entity_type": "person",
      "primary": true,
      "person_id": "~{\"chamber\": \"lower\", \"name\": \" C. Espenoza\"}",
      "organization_id": null
    },
    {
      "name": "Y. Zokaie",
      "classification": "sponsor",
      "entity_type": "person",
      "primary": true,
      "person_id": "~{\"chamber\": \"lower\", \"name\": \" Y. Zokaie\"}",
      "organization_id": null
    }
  ],
  "related_bills": [],
  "versions": [
    {
      "note": "Introduced",
      "links": [
        {
          "url": "https://leg.colorado.gov/bill_files/111531/download",
          "media_type": "application/pdf"
        }
      ],
      "date": "2026-02-09",
      "classification": ""
    }
  ],
  "documents": [],
  "citations": [],
  "sources": [
    {
      "url": "https://leg.colorado.gov/bills/HB26-1186",
      "note": ""
    }
  ],
  "extras": {},
  "jurisdiction": {
    "id": "ocd-jurisdiction/country:us/state:co/government",
    "name": "Colorado",
    "classification": "state",
    "division_id": "ocd-division/country:us/state:co"
  },
  "_processing": {
    "logs_latest_update": "2026-07-13T06:02:08Z"
  }
}